{
    "_updated": "2021-07-01",
    "curation": "https://static.toyobunko-lab.jp/suikeichuzu_data/curation/jouzu11_jushun.json",
    "fulltext": "CTSC(a)0-48, 「……」で表記される。, 道",
    "label": "道",
    "manifest": "https://static.toyobunko-lab.jp/suikeichuzu_data/iiif/jouzu11_jushun/manifest.json",
    "member": "https://app.toyobunko-lab.jp/iiif/2/jouzu11_jushun/canvas/p1#xywh=1709,2555,92,93",
    "objectID": "CTSC(a)0-48",
    "sort": [
        "04-00672"
    ],
    "thumbnail": "https://img.toyobunko-lab.jp/iiif/premodern_chinese/suikeichuzu/jouzu11_jushun.tif/1709,2555,92,93/200,/0/default.jpg",
    "備考": [
        "「……」で表記される。"
    ],
    "冊": [
        8
    ],
    "分類": [
        "なし"
    ],
    "区画南北": [
        0
    ],
    "区画東西": [
        0
    ],
    "図": [
        "寿春城図"
    ],
    "地名/記述": [
        "道"
    ],
    "墨朱": [
        "墨"
    ],
    "表裏": [
        "表"
    ],
    "記号": [
        0
    ],
    "記号説明": [
        ""
    ],
    "詳細区画": [
        0
    ]
}