{
    "fulltext": "沽河, 00-00549, 1, 北2, 西1, 本図, 沽河, 墨, 表, 1, C1",
    "group": [
        "main"
    ],
    "label": "沽河",
    "manifest": "https://nakamura196.github.io/suikeichuuzu/iiif/main/manifest.json",
    "member": "https://nakamura196.github.io/suikeichuuzu/iiif/main/canvas/p1#xywh=27623,3904,82,48",
    "objectID": "N2W1(a)C1-01",
    "sort": [
        "00-00549"
    ],
    "thumbnail": "https://img.toyobunko-lab.jp/iiif/premodern_chinese/suikeichuzu/Suikeichuuzu.tif/27623,3904,82,48/200,/0/default.jpg",
    "冊": [
        1
    ],
    "区画南北": [
        "北2"
    ],
    "区画東西": [
        "西1"
    ],
    "図": [
        "本図"
    ],
    "地名/記述": [
        "沽河"
    ],
    "墨朱": [
        "墨"
    ],
    "表裏": [
        "表"
    ],
    "記号": [
        1
    ],
    "詳細区画": [
        "C1"
    ]
}