{
    "fulltext": "大馬湖, 01-05672, 6, 南10, 西2, 本図, 大馬湖, 朱, 裏, 5, A2",
    "group": [
        "main"
    ],
    "label": "大馬湖",
    "manifest": "https://nakamura196.github.io/suikeichuuzu/iiif/main/manifest.json",
    "member": "https://nakamura196.github.io/suikeichuuzu/iiif/main/canvas/p1#xywh=23445,21988,91,30",
    "objectID": "S10W2(b)A2-05",
    "sort": [
        "01-05672"
    ],
    "thumbnail": "https://img.toyobunko-lab.jp/iiif/premodern_chinese/suikeichuzu/Suikeichuuzu.tif/23445,21988,91,30/200,/0/default.jpg",
    "冊": [
        6
    ],
    "区画南北": [
        "南10"
    ],
    "区画東西": [
        "西2"
    ],
    "図": [
        "本図"
    ],
    "地名/記述": [
        "大馬湖"
    ],
    "墨朱": [
        "朱"
    ],
    "表裏": [
        "裏"
    ],
    "記号": [
        5
    ],
    "詳細区画": [
        "A2"
    ]
}