{
    "fulltext": "陵子潭, 01-06489, 6, 南11, 西2, 本図, 陵子潭, 墨, 裏, 5, B3",
    "group": [
        "main"
    ],
    "label": "陵子潭",
    "manifest": "https://nakamura196.github.io/suikeichuuzu/iiif/main/manifest.json",
    "member": "https://nakamura196.github.io/suikeichuuzu/iiif/main/canvas/p1#xywh=23116,23948,50,36",
    "objectID": "S11W2(b)B3-18",
    "sort": [
        "01-06489"
    ],
    "thumbnail": "https://img.toyobunko-lab.jp/iiif/premodern_chinese/suikeichuzu/Suikeichuuzu.tif/23116,23948,50,36/200,/0/default.jpg",
    "冊": [
        6
    ],
    "区画南北": [
        "南11"
    ],
    "区画東西": [
        "西2"
    ],
    "図": [
        "本図"
    ],
    "地名/記述": [
        "陵子潭"
    ],
    "墨朱": [
        "墨"
    ],
    "表裏": [
        "裏"
    ],
    "記号": [
        5
    ],
    "詳細区画": [
        "B3"
    ]
}