{
    "fulltext": "馬龍, 01-08509, 7, 南14, 西8, 本図, 馬龍, 朱, 表, 23, C3",
    "group": [
        "main"
    ],
    "label": "馬龍",
    "manifest": "https://nakamura196.github.io/suikeichuuzu/iiif/main/manifest.json",
    "member": "https://nakamura196.github.io/suikeichuuzu/iiif/main/canvas/p1#xywh=10630,28770,60,38",
    "objectID": "S14W8(a)C3-02",
    "sort": [
        "01-08509"
    ],
    "thumbnail": "https://img.toyobunko-lab.jp/iiif/premodern_chinese/suikeichuzu/Suikeichuuzu.tif/10630,28770,60,38/200,/0/default.jpg",
    "冊": [
        7
    ],
    "区画南北": [
        "南14"
    ],
    "区画東西": [
        "西8"
    ],
    "図": [
        "本図"
    ],
    "地名/記述": [
        "馬龍"
    ],
    "墨朱": [
        "朱"
    ],
    "表裏": [
        "表"
    ],
    "記号": [
        23
    ],
    "詳細区画": [
        "C3"
    ]
}