{
    "fulltext": "南倇河, 01-09738, 8, 南16, 西9, 本図, 南倇河, 朱, 表, 1, C3",
    "group": [
        "main"
    ],
    "label": "南倇河",
    "manifest": "https://nakamura196.github.io/suikeichuuzu/iiif/main/manifest.json",
    "member": "https://nakamura196.github.io/suikeichuuzu/iiif/main/canvas/p1#xywh=8224,32008,109,43",
    "objectID": "S16W9(a)C3-01",
    "sort": [
        "01-09738"
    ],
    "thumbnail": "https://img.toyobunko-lab.jp/iiif/premodern_chinese/suikeichuzu/Suikeichuuzu.tif/8224,32008,109,43/200,/0/default.jpg",
    "冊": [
        8
    ],
    "区画南北": [
        "南16"
    ],
    "区画東西": [
        "西9"
    ],
    "図": [
        "本図"
    ],
    "地名/記述": [
        "南倇河"
    ],
    "墨朱": [
        "朱"
    ],
    "表裏": [
        "表"
    ],
    "記号": [
        1
    ],
    "詳細区画": [
        "C3"
    ]
}