{
    "fulltext": "雹水, 00-02613, 3, 南1, 西1, 本図, 雹水, 墨, 表, 1, A3",
    "group": [
        "main"
    ],
    "label": "雹水",
    "manifest": "https://nakamura196.github.io/suikeichuuzu/iiif/main/manifest.json",
    "member": "https://nakamura196.github.io/suikeichuuzu/iiif/main/canvas/p1#xywh=26742,7815,29,65",
    "objectID": "S1W1(a)A3-21",
    "sort": [
        "00-02613"
    ],
    "thumbnail": "https://img.toyobunko-lab.jp/iiif/premodern_chinese/suikeichuzu/Suikeichuuzu.tif/26742,7815,29,65/200,/0/default.jpg",
    "冊": [
        3
    ],
    "区画南北": [
        "南1"
    ],
    "区画東西": [
        "西1"
    ],
    "図": [
        "本図"
    ],
    "地名/記述": [
        "雹水"
    ],
    "墨朱": [
        "墨"
    ],
    "表裏": [
        "表"
    ],
    "記号": [
        1
    ],
    "詳細区画": [
        "A3"
    ]
}