{
    "fulltext": "三梁亭, 00-02640, 3, 南1, 西1, 本図, 三梁亭, 墨, 表, 16, B2",
    "group": [
        "main"
    ],
    "label": "三梁亭",
    "manifest": "https://nakamura196.github.io/suikeichuuzu/iiif/main/manifest.json",
    "member": "https://nakamura196.github.io/suikeichuuzu/iiif/main/canvas/p1#xywh=27017,8143,74,47",
    "objectID": "S1W1(a)B2-05",
    "sort": [
        "00-02640"
    ],
    "thumbnail": "https://img.toyobunko-lab.jp/iiif/premodern_chinese/suikeichuzu/Suikeichuuzu.tif/27017,8143,74,47/200,/0/default.jpg",
    "冊": [
        3
    ],
    "区画南北": [
        "南1"
    ],
    "区画東西": [
        "西1"
    ],
    "図": [
        "本図"
    ],
    "地名/記述": [
        "三梁亭"
    ],
    "墨朱": [
        "墨"
    ],
    "表裏": [
        "表"
    ],
    "記号": [
        16
    ],
    "詳細区画": [
        "B2"
    ]
}