{
    "_updated": "2021-06-30",
    "curation": "https://static.toyobunko-lab.jp/suikeichuzu_data/curation/main.json",
    "fulltext": "洞過水, S2W2(a)B3-01, 00-03753, 地形, 南2, 西2, 本図, 洞過水, 墨, 表, 河川, B3",
    "label": "洞過水",
    "manifest": "https://static.toyobunko-lab.jp/suikeichuzu_data/iiif/main/manifest.json",
    "member": "https://app.toyobunko-lab.jp/iiif/2/f772d9f6-2893-4b2c-8cd2-600f87b8583e/canvas/p1#xywh=24607,9880,45,118",
    "objectID": "S2W2(a)B3-01",
    "sort": [
        "00-03753"
    ],
    "thumbnail": "https://img.toyobunko-lab.jp/iiif/premodern_chinese/suikeichuzu/Suikeichuuzu_gousei_l.tif/24607,9880,45,118/200,/0/default.jpg",
    "冊": [
        3
    ],
    "分類": [
        "地形"
    ],
    "区画南北": [
        "南2"
    ],
    "区画東西": [
        "西2"
    ],
    "図": [
        "本図"
    ],
    "地名/記述": [
        "洞過水"
    ],
    "墨朱": [
        "墨"
    ],
    "表裏": [
        "表"
    ],
    "記号": [
        1
    ],
    "記号説明": [
        "河川"
    ],
    "詳細区画": [
        "B3"
    ]
}