{
    "fulltext": "蒲子, 00-05396, 4, 南3, 西3, 本図, 蒲子, 墨, 裏, 13, A1",
    "group": [
        "main"
    ],
    "label": "蒲子",
    "manifest": "https://nakamura196.github.io/suikeichuuzu/iiif/main/manifest.json",
    "member": "https://nakamura196.github.io/suikeichuuzu/iiif/main/canvas/p1#xywh=21672,11163,74,47",
    "objectID": "S3W3(b)A1-02",
    "sort": [
        "00-05396"
    ],
    "thumbnail": "https://img.toyobunko-lab.jp/iiif/premodern_chinese/suikeichuzu/Suikeichuuzu.tif/21672,11163,74,47/200,/0/default.jpg",
    "冊": [
        4
    ],
    "区画南北": [
        "南3"
    ],
    "区画東西": [
        "西3"
    ],
    "図": [
        "本図"
    ],
    "地名/記述": [
        "蒲子"
    ],
    "墨朱": [
        "墨"
    ],
    "表裏": [
        "裏"
    ],
    "記号": [
        13
    ],
    "詳細区画": [
        "A1"
    ]
}