{
    "fulltext": "塞外, 00-07825, 4, 南4, 西11, 本図, 塞外, 墨, 表, 0, C2",
    "group": [
        "main"
    ],
    "label": "塞外",
    "manifest": "https://nakamura196.github.io/suikeichuuzu/iiif/main/manifest.json",
    "member": "https://nakamura196.github.io/suikeichuuzu/iiif/main/canvas/p1#xywh=4008,13374,91,57",
    "objectID": "S4W11(a)C2-01",
    "sort": [
        "00-07825"
    ],
    "thumbnail": "https://img.toyobunko-lab.jp/iiif/premodern_chinese/suikeichuzu/Suikeichuuzu.tif/4008,13374,91,57/200,/0/default.jpg",
    "冊": [
        4
    ],
    "区画南北": [
        "南4"
    ],
    "区画東西": [
        "西11"
    ],
    "図": [
        "本図"
    ],
    "地名/記述": [
        "塞外"
    ],
    "墨朱": [
        "墨"
    ],
    "表裏": [
        "表"
    ],
    "記号": [
        0
    ],
    "詳細区画": [
        "C2"
    ]
}