{
    "fulltext": "漾水, 00-10812, 4, 南5, 西6, 本図, 漾水, 朱, 裏, 1, C2",
    "group": [
        "main"
    ],
    "label": "漾水",
    "manifest": "https://nakamura196.github.io/suikeichuuzu/iiif/main/manifest.json",
    "member": "https://nakamura196.github.io/suikeichuuzu/iiif/main/canvas/p1#xywh=14518,15124,59,35",
    "objectID": "S5W6(b)C2-07",
    "sort": [
        "00-10812"
    ],
    "thumbnail": "https://img.toyobunko-lab.jp/iiif/premodern_chinese/suikeichuzu/Suikeichuuzu.tif/14518,15124,59,35/200,/0/default.jpg",
    "冊": [
        4
    ],
    "区画南北": [
        "南5"
    ],
    "区画東西": [
        "西6"
    ],
    "図": [
        "本図"
    ],
    "地名/記述": [
        "漾水"
    ],
    "墨朱": [
        "朱"
    ],
    "表裏": [
        "裏"
    ],
    "記号": [
        1
    ],
    "詳細区画": [
        "C2"
    ]
}