{
    "_updated": "2021-06-30",
    "curation": "https://static.toyobunko-lab.jp/suikeichuzu_data/curation/main.json",
    "fulltext": "方城, S6W2(a)C3-02, 01-00608, 地点, 南6, 西2, 本図, 方城, 墨, 表, 亭台跡, C3",
    "label": "方城",
    "manifest": "https://static.toyobunko-lab.jp/suikeichuzu_data/iiif/main/manifest.json",
    "member": "https://app.toyobunko-lab.jp/iiif/2/f772d9f6-2893-4b2c-8cd2-600f87b8583e/canvas/p1#xywh=24446,16393,55,33",
    "objectID": "S6W2(a)C3-02",
    "sort": [
        "01-00608"
    ],
    "thumbnail": "https://img.toyobunko-lab.jp/iiif/premodern_chinese/suikeichuzu/Suikeichuuzu_gousei_l.tif/24446,16393,55,33/200,/0/default.jpg",
    "冊": [
        5
    ],
    "分類": [
        "地点"
    ],
    "区画南北": [
        "南6"
    ],
    "区画東西": [
        "西2"
    ],
    "図": [
        "本図"
    ],
    "地名/記述": [
        "方城"
    ],
    "墨朱": [
        "墨"
    ],
    "表裏": [
        "表"
    ],
    "記号": [
        16
    ],
    "記号説明": [
        "亭台跡"
    ],
    "詳細区画": [
        "C3"
    ]
}