{
    "fulltext": "木陵關, 01-03046, 5, 南8, 西1, 本図, 木陵關, 朱, 裏, 0, A1",
    "group": [
        "main"
    ],
    "label": "木陵關",
    "manifest": "https://nakamura196.github.io/suikeichuuzu/iiif/main/manifest.json",
    "member": "https://nakamura196.github.io/suikeichuuzu/iiif/main/canvas/p1#xywh=26189,18978,87,39",
    "objectID": "S8W1(b)A1-07",
    "sort": [
        "01-03046"
    ],
    "thumbnail": "https://img.toyobunko-lab.jp/iiif/premodern_chinese/suikeichuzu/Suikeichuuzu.tif/26189,18978,87,39/200,/0/default.jpg",
    "冊": [
        5
    ],
    "区画南北": [
        "南8"
    ],
    "区画東西": [
        "西1"
    ],
    "図": [
        "本図"
    ],
    "地名/記述": [
        "木陵關"
    ],
    "墨朱": [
        "朱"
    ],
    "表裏": [
        "裏"
    ],
    "記号": [
        0
    ],
    "詳細区画": [
        "A1"
    ]
}