{
    "fulltext": "即荊山首, 01-03327, 5, 南8, 西3, 本図, 即荊山首, 墨, 裏, 4, B2",
    "group": [
        "main"
    ],
    "label": "即荊山首",
    "manifest": "https://nakamura196.github.io/suikeichuuzu/iiif/main/manifest.json",
    "member": "https://nakamura196.github.io/suikeichuuzu/iiif/main/canvas/p1#xywh=21192,19345,129,43",
    "objectID": "S8W3(b)B2-05",
    "sort": [
        "01-03327"
    ],
    "thumbnail": "https://img.toyobunko-lab.jp/iiif/premodern_chinese/suikeichuzu/Suikeichuuzu.tif/21192,19345,129,43/200,/0/default.jpg",
    "冊": [
        5
    ],
    "区画南北": [
        "南8"
    ],
    "区画東西": [
        "西3"
    ],
    "図": [
        "本図"
    ],
    "地名/記述": [
        "即荊山首"
    ],
    "墨朱": [
        "墨"
    ],
    "表裏": [
        "裏"
    ],
    "記号": [
        4
    ],
    "詳細区画": [
        "B2"
    ]
}