{
    "fulltext": "沙河, 01-03519, 5, 南8, 西5, 本図, 沙河, 朱, 裏, 1, D1",
    "group": [
        "main"
    ],
    "label": "沙河",
    "manifest": "https://nakamura196.github.io/suikeichuuzu/iiif/main/manifest.json",
    "member": "https://nakamura196.github.io/suikeichuuzu/iiif/main/canvas/p1#xywh=17005,20163,67,40",
    "objectID": "S8W5(b)D1-02",
    "sort": [
        "01-03519"
    ],
    "thumbnail": "https://img.toyobunko-lab.jp/iiif/premodern_chinese/suikeichuzu/Suikeichuuzu.tif/17005,20163,67,40/200,/0/default.jpg",
    "冊": [
        5
    ],
    "区画南北": [
        "南8"
    ],
    "区画東西": [
        "西5"
    ],
    "図": [
        "本図"
    ],
    "地名/記述": [
        "沙河"
    ],
    "墨朱": [
        "朱"
    ],
    "表裏": [
        "裏"
    ],
    "記号": [
        1
    ],
    "詳細区画": [
        "D1"
    ]
}