{
    "fulltext": "牛鞞水, 01-05021, 6, 南9, 西7, 本図, 牛鞞水, 墨, 表, 1, C3",
    "group": [
        "main"
    ],
    "label": "牛鞞水",
    "manifest": "https://nakamura196.github.io/suikeichuuzu/iiif/main/manifest.json",
    "member": "https://nakamura196.github.io/suikeichuuzu/iiif/main/canvas/p1#xywh=12786,21102,55,114",
    "objectID": "S9W7(a)C3-01",
    "sort": [
        "01-05021"
    ],
    "thumbnail": "https://img.toyobunko-lab.jp/iiif/premodern_chinese/suikeichuzu/Suikeichuuzu.tif/12786,21102,55,114/200,/0/default.jpg",
    "冊": [
        6
    ],
    "区画南北": [
        "南9"
    ],
    "区画東西": [
        "西7"
    ],
    "図": [
        "本図"
    ],
    "地名/記述": [
        "牛鞞水"
    ],
    "墨朱": [
        "墨"
    ],
    "表裏": [
        "表"
    ],
    "記号": [
        1
    ],
    "詳細区画": [
        "C3"
    ]
}