{
    "_updated": "2021-06-29",
    "curation": "https://static.toyobunko-lab.jp/suikeichuzu_data/curation/saiiki.json",
    "fulltext": "阿耨達大水, 02-00072, 地形, 上, 西域, 阿耨達大水, 墨, 表, 河川, C3",
    "label": "阿耨達大水",
    "manifest": "https://static.toyobunko-lab.jp/suikeichuzu_data/iiif/saiiki/manifest.json",
    "member": "https://app.toyobunko-lab.jp/iiif/2/f75e3194-194f-443c-bfa4-6eb50568c5ef/canvas/p1#xywh=7236,2322,228,171",
    "objectID": "XT1(a)C3-02",
    "sort": [
        "02-00072"
    ],
    "thumbnail": "https://img.toyobunko-lab.jp/iiif/premodern_chinese/suikeichuzu/1_003_Saiiki_gousei_l.tif/7236,2322,228,171/200,/0/default.jpg",
    "冊": [
        1
    ],
    "分類": [
        "地形"
    ],
    "区画南北": [
        "上"
    ],
    "区画東西": [
        1
    ],
    "図": [
        "西域"
    ],
    "地名/記述": [
        "阿耨達大水"
    ],
    "墨朱": [
        "墨"
    ],
    "表裏": [
        "表"
    ],
    "記号": [
        1
    ],
    "記号説明": [
        "河川"
    ],
    "詳細区画": [
        "C3"
    ]
}