{
    "fulltext": "平門, 04-00337, 8, 0, 0, 長安城図, 平門, 墨, 裏, 34, 0",
    "group": [
        "jouzu04_chouan"
    ],
    "label": "平門",
    "manifest": "https://nakamura196.github.io/suikeichuuzu/iiif/jouzu04_chouan/manifest.json",
    "member": "https://nakamura196.github.io/suikeichuuzu/iiif/jouzu04_chouan/manifest.json/canvas/p1#xywh=1420,2557,136,74",
    "objectID": "CTCA(b)0-43",
    "sort": [
        "04-00337"
    ],
    "thumbnail": "https://img.toyobunko-lab.jp/iiif/premodern_chinese/suikeichuzu/jouzu04_chouan.tif/1420,2557,136,74/200,/0/default.jpg",
    "冊": [
        8
    ],
    "区画南北": [
        0
    ],
    "区画東西": [
        0
    ],
    "図": [
        "長安城図"
    ],
    "地名/記述": [
        "平門"
    ],
    "墨朱": [
        "墨"
    ],
    "表裏": [
        "裏"
    ],
    "記号": [
        34
    ],
    "詳細区画": [
        0
    ]
}