{
    "curation": "https://static.toyobunko-lab.jp/suikeichuzu_data/curation/jouzu03_rakuyou.json",
    "fulltext": "CTLY(b)0-141, 04-00224, なし, 雒陽城図, 雒陽茄蓝記京狮東捿貳十裡南北十五裡, 㱄, 裡, 穀水, 巻16",
    "label": "洛陽伽藍記京師東西二十里南北十五里",
    "manifest": "https://static.toyobunko-lab.jp/suikeichuzu_data/iiif/jouzu03_rakuyou/manifest.json",
    "member": "https://app.toyobunko-lab.jp/iiif/2/jouzu03_rakuyou/canvas/p1#xywh=719,1949,364,286",
    "objectID": "CTLY(b)0-141",
    "sort": [
        "04-00224"
    ],
    "thumbnail": "https://img.toyobunko-lab.jp/iiif/premodern_chinese/suikeichuzu/jouzu03_rakuyou.tif/719,1949,364,286/200,/0/default.jpg",
    "冊": [
        8
    ],
    "分類": [
        "なし"
    ],
    "区画南北": [
        0
    ],
    "区画東西": [
        0
    ],
    "図": [
        "洛陽城図"
    ],
    "地名/記述": [
        "洛陽伽藍記京師東西二十里南北十五里"
    ],
    "墨朱": [
        "墨"
    ],
    "水名": [
        "穀水"
    ],
    "水経注図：冊子画像": [
        "http://www.toyo-bunko.or.jp/research/ss/iiif/mirador/?manifest=https://static.toyobunko-lab.jp/suikeichuzu_data/iiif/sjzt_8/manifest.json&canvas=http://www.toyo-bunko.or.jp/research/ss/iiif/item/sjzt_8.json/canvas/p36"
    ],
    "水経注：巻": [
        "巻16"
    ],
    "表裏": [
        "裏"
    ],
    "記号": [
        0
    ],
    "記号説明": [
        ""
    ],
    "詳細区画": [
        0
    ]
}