{
    "_updated": "2021-06-29",
    "curation": "https://static.toyobunko-lab.jp/suikeichuzu_data/curation/main.json",
    "fulltext": "東漢定襄郡, 00-01263, 行政, 北1, 西2, 本図, 東漢定襄郡, 墨, 裏, 州郡跡, D2",
    "label": "東漢定襄郡",
    "manifest": "https://static.toyobunko-lab.jp/suikeichuzu_data/iiif/main/manifest.json",
    "member": "https://app.toyobunko-lab.jp/iiif/2/f772d9f6-2893-4b2c-8cd2-600f87b8583e/canvas/p1#xywh=23573,5930,146,37",
    "objectID": "N1W2(b)D2-08",
    "sort": [
        "00-01263"
    ],
    "thumbnail": "https://img.toyobunko-lab.jp/iiif/premodern_chinese/suikeichuzu/Suikeichuuzu_gousei_l.tif/23573,5930,146,37/200,/0/default.jpg",
    "冊": [
        2
    ],
    "分類": [
        "行政"
    ],
    "区画南北": [
        "北1"
    ],
    "区画東西": [
        "西2"
    ],
    "図": [
        "本図"
    ],
    "地名/記述": [
        "東漢定襄郡"
    ],
    "墨朱": [
        "墨"
    ],
    "表裏": [
        "裏"
    ],
    "記号": [
        9
    ],
    "記号説明": [
        "州郡跡"
    ],
    "詳細区画": [
        "D2"
    ]
}