{
    "fulltext": "枝瀆入沅, 01-05830, 6, 南10, 西3, 本図, 枝瀆入沅, 墨, 表, 1, D1",
    "group": [
        "main"
    ],
    "label": "枝瀆入沅",
    "manifest": "https://nakamura196.github.io/suikeichuuzu/iiif/main/manifest.json",
    "member": "https://nakamura196.github.io/suikeichuuzu/iiif/main/canvas/p1#xywh=22704,22935,57,70",
    "objectID": "S10W3(a)D1-01",
    "sort": [
        "01-05830"
    ],
    "thumbnail": "https://img.toyobunko-lab.jp/iiif/premodern_chinese/suikeichuzu/Suikeichuuzu.tif/22704,22935,57,70/200,/0/default.jpg",
    "冊": [
        6
    ],
    "区画南北": [
        "南10"
    ],
    "区画東西": [
        "西3"
    ],
    "図": [
        "本図"
    ],
    "地名/記述": [
        "枝瀆入沅"
    ],
    "墨朱": [
        "墨"
    ],
    "表裏": [
        "表"
    ],
    "記号": [
        1
    ],
    "詳細区画": [
        "D1"
    ]
}