{
    "curation": "https://static.toyobunko-lab.jp/suikeichuzu_data/curation/main.json",
    "fulltext": "S14W2(a)D3-01, 01-08132, なし, 南14, 西2, 本図, 鼻天子城, 墨, 表, , D3溱水, 耒水, 贛水, 巻38, 巻39",
    "label": "鼻天子城",
    "manifest": "https://static.toyobunko-lab.jp/suikeichuzu_data/iiif/main/manifest.json",
    "member": "https://app.toyobunko-lab.jp/iiif/2/f772d9f6-2893-4b2c-8cd2-600f87b8583e/canvas/p1#xywh=24468,29460,108,56",
    "objectID": "S14W2(a)D3-01",
    "sort": [
        "01-08132"
    ],
    "thumbnail": "https://img.toyobunko-lab.jp/iiif/premodern_chinese/suikeichuzu/Suikeichuuzu_gousei_l.tif/24468,29460,108,56/200,/0/default.jpg",
    "冊": [
        7
    ],
    "分類": [
        "なし"
    ],
    "区画南北": [
        "南14"
    ],
    "区画東西": [
        "西2"
    ],
    "図": [
        "本図"
    ],
    "地名/記述": [
        "鼻天子城"
    ],
    "墨朱": [
        "墨"
    ],
    "水名": [
        "溱水",
        "耒水",
        "贛水"
    ],
    "水経注図：冊子画像": [
        "http://www.toyo-bunko.or.jp/research/ss/iiif/mirador/?manifest=https://static.toyobunko-lab.jp/suikeichuzu_data/iiif/sjzt_7/manifest.json&canvas=http://www.toyo-bunko.or.jp/research/ss/iiif/item/sjzt_7.json/canvas/p26"
    ],
    "水経注：巻": [
        "巻38",
        "巻39"
    ],
    "表裏": [
        "表"
    ],
    "記号": [
        0
    ],
    "記号説明": [
        ""
    ],
    "詳細区画": [
        "D3"
    ]
}