{
    "curation": "https://static.toyobunko-lab.jp/suikeichuzu_data/curation/main.json",
    "fulltext": "S17W8(a)B2-01, 01-09964, 嶳形, 南17, 捿8, 㮺図, 賭咒河, 朱, 表, 河巛, B2葉榆水, 巻37",
    "label": "賭咒河",
    "manifest": "https://static.toyobunko-lab.jp/suikeichuzu_data/iiif/main/manifest.json",
    "member": "https://app.toyobunko-lab.jp/iiif/2/f772d9f6-2893-4b2c-8cd2-600f87b8583e/canvas/p1#xywh=11058,33045,101,38",
    "objectID": "S17W8(a)B2-01",
    "sort": [
        "01-09964"
    ],
    "thumbnail": "https://img.toyobunko-lab.jp/iiif/premodern_chinese/suikeichuzu/Suikeichuuzu_gousei_l.tif/11058,33045,101,38/200,/0/default.jpg",
    "冊": [
        8
    ],
    "分類": [
        "地形"
    ],
    "区画南北": [
        "南17"
    ],
    "区画東西": [
        "西8"
    ],
    "図": [
        "本図"
    ],
    "地名/記述": [
        "賭咒河"
    ],
    "墨朱": [
        "朱"
    ],
    "水名": [
        "葉榆水"
    ],
    "水経注図：冊子画像": [
        "http://www.toyo-bunko.or.jp/research/ss/iiif/mirador/?manifest=https://static.toyobunko-lab.jp/suikeichuzu_data/iiif/sjzt_8/manifest.json&canvas=http://www.toyo-bunko.or.jp/research/ss/iiif/item/sjzt_8.json/canvas/p18"
    ],
    "水経注：巻": [
        "巻37"
    ],
    "表裏": [
        "表"
    ],
    "記号": [
        1
    ],
    "記号説明": [
        "河川"
    ],
    "詳細区画": [
        "B2"
    ]
}