{
    "fulltext": "陰安, 00-05027, 4, 南3, 西1, 本図, 陰安, 墨, 表, 10, D2",
    "group": [
        "main"
    ],
    "label": "陰安",
    "manifest": "https://nakamura196.github.io/suikeichuuzu/iiif/main/manifest.json",
    "member": "https://nakamura196.github.io/suikeichuuzu/iiif/main/canvas/p1#xywh=27025,12251,74,43",
    "objectID": "S3W1(a)D2-04",
    "sort": [
        "00-05027"
    ],
    "thumbnail": "https://img.toyobunko-lab.jp/iiif/premodern_chinese/suikeichuzu/Suikeichuuzu.tif/27025,12251,74,43/200,/0/default.jpg",
    "冊": [
        4
    ],
    "区画南北": [
        "南3"
    ],
    "区画東西": [
        "西1"
    ],
    "図": [
        "本図"
    ],
    "地名/記述": [
        "陰安"
    ],
    "墨朱": [
        "墨"
    ],
    "表裏": [
        "表"
    ],
    "記号": [
        10
    ],
    "詳細区画": [
        "D2"
    ]
}