{
    "fulltext": "金郷, 00-06268, 4, 南4, 中, 本図, 金郷, 朱, 裏, 19, D2",
    "group": [
        "main"
    ],
    "label": "金郷",
    "manifest": "https://nakamura196.github.io/suikeichuuzu/iiif/main/manifest.json",
    "member": "https://nakamura196.github.io/suikeichuuzu/iiif/main/canvas/p1#xywh=28411,13723,63,53",
    "objectID": "S4C(b)D2-02",
    "sort": [
        "00-06268"
    ],
    "thumbnail": "https://img.toyobunko-lab.jp/iiif/premodern_chinese/suikeichuzu/Suikeichuuzu.tif/28411,13723,63,53/200,/0/default.jpg",
    "冊": [
        4
    ],
    "区画南北": [
        "南4"
    ],
    "区画東西": [
        "中"
    ],
    "図": [
        "本図"
    ],
    "地名/記述": [
        "金郷"
    ],
    "墨朱": [
        "朱"
    ],
    "表裏": [
        "裏"
    ],
    "記号": [
        19
    ],
    "詳細区画": [
        "D2"
    ]
}