{
    "fulltext": "清口, 00-06556, 4, 南4, 西1, 本図, 清口, 墨, 裏, 0, B2",
    "group": [
        "main"
    ],
    "label": "清口",
    "manifest": "https://nakamura196.github.io/suikeichuuzu/iiif/main/manifest.json",
    "member": "https://nakamura196.github.io/suikeichuuzu/iiif/main/canvas/p1#xywh=26057,13131,66,47",
    "objectID": "S4W1(b)B2-21",
    "sort": [
        "00-06556"
    ],
    "thumbnail": "https://img.toyobunko-lab.jp/iiif/premodern_chinese/suikeichuzu/Suikeichuuzu.tif/26057,13131,66,47/200,/0/default.jpg",
    "冊": [
        4
    ],
    "区画南北": [
        "南4"
    ],
    "区画東西": [
        "西1"
    ],
    "図": [
        "本図"
    ],
    "地名/記述": [
        "清口"
    ],
    "墨朱": [
        "墨"
    ],
    "表裏": [
        "裏"
    ],
    "記号": [
        0
    ],
    "詳細区画": [
        "B2"
    ]
}