{
    "fulltext": "涇河, 00-07464, 4, 南4, 西5, 本図, 涇河, 朱, 表, 1, D3",
    "group": [
        "main"
    ],
    "label": "涇河",
    "manifest": "https://nakamura196.github.io/suikeichuuzu/iiif/main/manifest.json",
    "member": "https://nakamura196.github.io/suikeichuuzu/iiif/main/canvas/p1#xywh=17558,13640,77,81",
    "objectID": "S4W5(a)D3-01",
    "sort": [
        "00-07464"
    ],
    "thumbnail": "https://img.toyobunko-lab.jp/iiif/premodern_chinese/suikeichuzu/Suikeichuuzu.tif/17558,13640,77,81/200,/0/default.jpg",
    "冊": [
        4
    ],
    "区画南北": [
        "南4"
    ],
    "区画東西": [
        "西5"
    ],
    "図": [
        "本図"
    ],
    "地名/記述": [
        "涇河"
    ],
    "墨朱": [
        "朱"
    ],
    "表裏": [
        "表"
    ],
    "記号": [
        1
    ],
    "詳細区画": [
        "D3"
    ]
}