{
    "_updated": "2021-07-01",
    "curation": "https://static.toyobunko-lab.jp/suikeichuzu_data/curation/main.json",
    "fulltext": "S5W4(b)C1-26, 神井",
    "label": "神井",
    "manifest": "https://static.toyobunko-lab.jp/suikeichuzu_data/iiif/main/manifest.json",
    "member": "https://app.toyobunko-lab.jp/iiif/2/f772d9f6-2893-4b2c-8cd2-600f87b8583e/canvas/p1#xywh=19278,15010,45,46",
    "objectID": "S5W4(b)C1-26",
    "sort": [
        "00-10031"
    ],
    "thumbnail": "https://img.toyobunko-lab.jp/iiif/premodern_chinese/suikeichuzu/Suikeichuuzu_gousei_l.tif/19278,15010,45,46/200,/0/default.jpg",
    "冊": [
        4
    ],
    "分類": [
        "地形"
    ],
    "区画南北": [
        "南5"
    ],
    "区画東西": [
        "西4"
    ],
    "図": [
        "本図"
    ],
    "地名/記述": [
        "神井"
    ],
    "墨朱": [
        "墨"
    ],
    "表裏": [
        "裏"
    ],
    "記号": [
        5
    ],
    "記号説明": [
        "湖"
    ],
    "詳細区画": [
        "C1"
    ]
}