{
    "fulltext": "經潛水, 01-03531, 5, 南8, 西6, 本図, 經潛水, 墨, 表, 1, B1",
    "group": [
        "main"
    ],
    "label": "經潛水",
    "manifest": "https://nakamura196.github.io/suikeichuuzu/iiif/main/manifest.json",
    "member": "https://nakamura196.github.io/suikeichuuzu/iiif/main/canvas/p1#xywh=15829,19028,118,42",
    "objectID": "S8W6(a)B1-01",
    "sort": [
        "01-03531"
    ],
    "thumbnail": "https://img.toyobunko-lab.jp/iiif/premodern_chinese/suikeichuzu/Suikeichuuzu.tif/15829,19028,118,42/200,/0/default.jpg",
    "冊": [
        5
    ],
    "区画南北": [
        "南8"
    ],
    "区画東西": [
        "西6"
    ],
    "図": [
        "本図"
    ],
    "地名/記述": [
        "經潛水"
    ],
    "墨朱": [
        "墨"
    ],
    "表裏": [
        "表"
    ],
    "記号": [
        1
    ],
    "詳細区画": [
        "B1"
    ]
}