{
    "curation": "https://static.toyobunko-lab.jp/suikeichuzu_data/curation/ukou.json",
    "fulltext": "YG(a)0-60, 05-00060, 行政, 禹贡山沝襗嶳所在, 陶鄴, 㱄, 表, 县跡",
    "label": "陶邱",
    "manifest": "https://static.toyobunko-lab.jp/suikeichuzu_data/iiif/ukou/manifest.json",
    "member": "https://app.toyobunko-lab.jp/iiif/2/49946ae5-c6f8-4bbe-92d5-5a70c211b9ca/canvas/p1#xywh=2664,881,57,63",
    "objectID": "YG(a)0-60",
    "sort": [
        "05-00060"
    ],
    "thumbnail": "https://img.toyobunko-lab.jp/iiif/premodern_chinese/suikeichuzu/Ukou.tif/2664,881,57,63/200,/0/default.jpg",
    "冊": [
        8
    ],
    "分類": [
        "行政"
    ],
    "区画南北": [
        0
    ],
    "区画東西": [
        0
    ],
    "図": [
        "禹貢山水澤地所在"
    ],
    "地名/記述": [
        "陶邱"
    ],
    "墨朱": [
        "墨"
    ],
    "表裏": [
        "表"
    ],
    "記号": [
        10
    ],
    "記号説明": [
        "県跡"
    ],
    "詳細区画": [
        0
    ]
}